rayycli/__init__.py
rayycli/logic.py
rayycli/ractf/__init__.py
rayycli/ractf/abc.py
rayycli/ractf/category.py
rayycli/ractf/challenge.py
rayycli/ractf/ctf.py
rayycli/ractf/errors.py
rayycli/ractf/file.py
rayycli/ractf/helpers/requests.py
rayycli/ractf/hint.py
rayycli/rayycli.py
rayycli/utils/files.py
rayycli/utils/log.py
rayycli-0.1.2.dist-info/entry_points.txt
rayycli-0.1.2.dist-info/WHEEL
rayycli-0.1.2.dist-info/METADATA
rayycli-0.1.2.dist-info/RECORD
