Metadata-Version: 2.1
Name: rayycli
Version: 0.1.2
Summary: 
License: MIT
Author: Jeremiah Boby
Author-email: mail@jeremiahboby.me
Requires-Python: >=3.8,<4.0
Classifier: License :: OSI Approved :: MIT License
Classifier: Programming Language :: Python :: 3
Classifier: Programming Language :: Python :: 3.8
Classifier: Programming Language :: Python :: 3.9
Requires-Dist: click (>=7.1.2,<8.0.0)
